lncn.py
lncn-0.2.0.dist-info/METADATA
lncn-0.2.0.dist-info/WHEEL
lncn-0.2.0.dist-info/entry_points.txt
lncn-0.2.0.dist-info/top_level.txt
lncn-0.2.0.dist-info/RECORD
