Metadata-Version: 2.4
Name: lncn
Version: 0.2.0
Summary: Simple Python CLI to count SLOC in a codebase
Home-page: https://github.com/qque/lncn
Author: qque
Dynamic: author
Dynamic: description
Dynamic: description-content-type
Dynamic: home-page
Dynamic: summary
